Products.membrane-7.0.0-py3.12-nspkg.pth
Products/membrane/__init__.py
Products/membrane/catalog.py
Products/membrane/config.py
Products/membrane/configure.zcml
Products/membrane/events.py
Products/membrane/permissions.py
Products/membrane/permissions.zcml
Products/membrane/setuphandlers.py
Products/membrane/testing.py
Products/membrane/tool.gif
Products/membrane/utils.py
Products/membrane/browser/__init__.py
Products/membrane/browser/configure.zcml
Products/membrane/browser/membrane_types.pt
Products/membrane/browser/tool_zmi_views.py
Products/membrane/exportimport/__init__.py
Products/membrane/exportimport/configure.zcml
Products/membrane/exportimport/membranetool.py
Products/membrane/interfaces/__init__.py
Products/membrane/interfaces/configure.zcml
Products/membrane/interfaces/events.py
Products/membrane/interfaces/group.py
Products/membrane/interfaces/membrane_tool.py
Products/membrane/interfaces/plugins.py
Products/membrane/interfaces/user.py
Products/membrane/interfaces/utilities.py
Products/membrane/plugins/__init__.py
Products/membrane/plugins/groupmanager.py
Products/membrane/plugins/propertymanager.py
Products/membrane/plugins/rolemanager.py
Products/membrane/plugins/userfactory.py
Products/membrane/plugins/usermanager.py
Products/membrane/profiles/default/membrane-setup-plugins.txt
Products/membrane/profiles/default/membrane_tool.xml
Products/membrane/profiles/default/metadata.xml
Products/membrane/profiles/default/toolset.xml
Products/membrane/profiles/uninstall/toolset.xml
Products/membrane/tests/__init__.py
Products/membrane/tests/base.py
Products/membrane/tests/dummy.py
Products/membrane/tests/testMembraneCatalog.py
Products/membrane/tests/testMembraneGroupManager.py
Products/membrane/tests/testMembranePropertyManager.py
Products/membrane/tests/testMembraneRoleManager.py
Products/membrane/tests/testMembraneSearch.py
Products/membrane/tests/testMembraneTool.py
Products/membrane/tests/testMembraneUserFactory.py
products_membrane-7.0.0.dist-info/METADATA
products_membrane-7.0.0.dist-info/WHEEL
products_membrane-7.0.0.dist-info/namespace_packages.txt
products_membrane-7.0.0.dist-info/top_level.txt
products_membrane-7.0.0.dist-info/RECORD
